{"document_sentiment": {"magnitude": 2.799999952316284, "score": 0.20000000298023224}, "language": "en", "sentences": [{"text": {"content": "Letter: TO MRS."}, "sentiment": {}}, {"text": {"content": "BAKER", "begin_offset": 16}, "sentiment": {}}, {"text": {"content": "VAILIMA, SAMOA, JULY 16, 1894.", "begin_offset": 23}, "sentiment": {}}, {"text": {"content": "DEAR MRS.", "begin_offset": 54}, "sentiment": {"magnitude": 0.10000000149011612, "score": 0.10000000149011612}}, {"text": {"content": "BAKER, - I am very much obliged to you for your letter and the enclosure from Mr. Skinner.", "begin_offset": 64}, "sentiment": {}}, {"text": {"content": "Mr. Skinner says he 'thinks Mr. Stevenson must be a very kind man'; he little knows me.", "begin_offset": 155}, "sentiment": {}}, {"text": {"content": "But I am very sure of one thing, that you are a very kind woman.", "begin_offset": 243}, "sentiment": {"magnitude": 0.5, "score": 0.5}}, {"text": {"content": "I envy you - my amanuensis being called away, I continue in my own hand, or what is left of it - unusually legible, I am thankful to see - I envy you your beautiful choice of an employment.", "begin_offset": 308}, "sentiment": {"magnitude": 0.800000011920929, "score": 0.800000011920929}}, {"text": {"content": "There must be no regrets at least for a day so spent; and when the night falls you need ask no blessing on your work.", "begin_offset": 498}, "sentiment": {"magnitude": 0.800000011920929, "score": 0.800000011920929}}, {"text": {"content": "'Inasmuch as ye have done it unto one of these.'", "begin_offset": 616}, "sentiment": {}}, {"text": {"content": "- Yours truly,\nROBERT LOUIS STEVENSON.", "begin_offset": 665}, "sentiment": {"magnitude": 0.10000000149011612, "score": 0.10000000149011612}}]}