[{"name": "MR", "type": 1, "salience": 0.09762720763683319, "mentions": [{"text": {"content": "MR", "begin_offset": 11}, "type": 2}]}, {"name": "Letter", "type": 5, "salience": 0.09762720763683319, "mentions": [{"text": {"content": "Letter"}, "type": 2}]}, {"name": "thing", "type": 7, "salience": 0.09376512467861176, "mentions": [{"text": {"content": "thing", "begin_offset": 904}, "type": 2}]}, {"name": "fault", "type": 7, "salience": 0.060216017067432404, "mentions": [{"text": {"content": "fault", "begin_offset": 119}, "type": 2}]}, {"name": "MRS", "type": 1, "salience": 0.04678267240524292, "mentions": [{"text": {"content": "MRS", "begin_offset": 19}, "type": 2}]}, {"name": "PEOPLE", "type": 1, "salience": 0.04624636471271515, "mentions": [{"text": {"content": "PEOPLE", "begin_offset": 91}, "type": 2}]}, {"name": "leakage", "type": 4, "salience": 0.04518890008330345, "mentions": [{"text": {"content": "leakage", "begin_offset": 313}, "type": 2}]}, {"name": "BOURNEMOUTH", "type": 2, "metadata": {"mid": "/m/0161jj", "wikipedia_url": "https://en.wikipedia.org/wiki/Bournemouth"}, "salience": 0.03145541623234749, "mentions": [{"text": {"content": "BOURNEMOUTH", "begin_offset": 54}, "type": 1}, {"text": {"content": "Bournemouth", "begin_offset": 220}, "type": 1}]}, {"name": "inn", "type": 2, "salience": 0.030190547928214073, "mentions": [{"text": {"content": "inn", "begin_offset": 427}, "type": 2}]}, {"name": "THOMAS STEVENSON", "type": 1, "metadata": {"mid": "/m/03jb1l", "wikipedia_url": "https://en.wikipedia.org/wiki/Thomas_Stevenson"}, "salience": 0.027636943385004997, "mentions": [{"text": {"content": "THOMAS STEVENSON", "begin_offset": 24}, "type": 1}]}, {"name": "SKERRYVORE", "type": 3, "metadata": {"wikipedia_url": "https://en.wikipedia.org/wiki/Skerryvore_(band)", "mid": "/m/0nhsxm3"}, "salience": 0.027536749839782715, "mentions": [{"text": {"content": "SKERRYVORE", "begin_offset": 42}, "type": 1}]}, {"name": "JULY 7TH", "type": 7, "metadata": {"mid": "/m/041dm", "wikipedia_url": "https://en.wikipedia.org/wiki/July_7"}, "salience": 0.027536749839782715, "mentions": [{"text": {"content": "JULY 7TH", "begin_offset": 67}, "type": 1}]}, {"name": "house", "type": 2, "salience": 0.02110579051077366, "mentions": [{"text": {"content": "house", "begin_offset": 259}, "type": 2}]}, {"name": "course", "type": 7, "salience": 0.020163830369710922, "mentions": [{"text": {"content": "course", "begin_offset": 339}, "type": 2}]}, {"name": "discussion", "type": 4, "salience": 0.017681974917650223, "mentions": [{"text": {"content": "discussion", "begin_offset": 298}, "type": 2}]}, {"name": "things", "type": 7, "salience": 0.014928114600479603, "mentions": [{"text": {"content": "things", "begin_offset": 687}, "type": 2}]}, {"name": "thing", "type": 7, "salience": 0.014908227138221264, "mentions": [{"text": {"content": "thing", "begin_offset": 716}, "type": 2}]}, {"name": "course", "type": 7, "salience": 0.013579978607594967, "mentions": [{"text": {"content": "course", "begin_offset": 582}, "type": 2}]}, {"name": "box", "type": 7, "salience": 0.011883605271577835, "mentions": [{"text": {"content": "box", "begin_offset": 626}, "type": 2}]}, {"name": "heat", "type": 7, "salience": 0.011883605271577835, "mentions": [{"text": {"content": "heat", "begin_offset": 648}, "type": 2}]}, {"name": "deal", "type": 7, "salience": 0.011883605271577835, "mentions": [{"text": {"content": "deal", "begin_offset": 661}, "type": 2}]}, {"name": "notion", "type": 7, "salience": 0.01162341982126236, "mentions": [{"text": {"content": "notion", "begin_offset": 377}, "type": 2}]}, {"name": "mixture", "type": 7, "salience": 0.010861261747777462, "mentions": [{"text": {"content": "mixture", "begin_offset": 753}, "type": 2}]}, {"name": "idol", "type": 1, "salience": 0.010861261747777462, "mentions": [{"text": {"content": "idol", "begin_offset": 773}, "type": 2}]}, {"name": "lion", "type": 7, "salience": 0.010861261747777462, "mentions": [{"text": {"content": "lion", "begin_offset": 781}, "type": 2}]}, {"name": "woman", "type": 1, "salience": 0.010861261747777462, "mentions": [{"text": {"content": "woman", "begin_offset": 810}, "type": 2}]}, {"name": "whistle", "type": 6, "salience": 0.009236674755811691, "mentions": [{"text": {"content": "whistle", "begin_offset": 1087}, "type": 2}]}, {"name": "figure", "type": 7, "salience": 0.009096706286072731, "mentions": [{"text": {"content": "figure", "begin_offset": 857}, "type": 2}]}, {"name": "climes", "type": 7, "salience": 0.008082094602286816, "mentions": [{"text": {"content": "climes", "begin_offset": 1185}, "type": 2}]}, {"name": "quest", "type": 7, "salience": 0.008082094602286816, "mentions": [{"text": {"content": "quest", "begin_offset": 1167}, "type": 2}]}, {"name": "half", "type": 7, "salience": 0.008082094602286816, "mentions": [{"text": {"content": "half", "begin_offset": 1143}, "type": 2}]}, {"name": "furlong", "type": 7, "salience": 0.008082094602286816, "mentions": [{"text": {"content": "furlong", "begin_offset": 1129}, "type": 2}]}, {"name": "neighbours", "type": 1, "salience": 0.008082094602286816, "mentions": [{"text": {"content": "neighbours", "begin_offset": 1100}, "type": 2}]}, {"name": "radius", "type": 7, "salience": 0.008082094602286816, "mentions": [{"text": {"content": "radius", "begin_offset": 1117}, "type": 2}]}, {"name": "money", "type": 7, "salience": 0.007966870442032814, "mentions": [{"text": {"content": "money", "begin_offset": 1267}, "type": 2}]}, {"name": "Alexander", "type": 1, "salience": 0.0070295012556016445, "mentions": [{"text": {"content": "Alexander", "begin_offset": 695}, "type": 1}]}, {"name": "Kirkmichael", "type": 2, "metadata": {"wikipedia_url": "https://en.wikipedia.org/wiki/Kirkmichael,_Perth_and_Kinross", "mid": "/m/02r4yxy"}, "salience": 0.006972437258809805, "mentions": [{"text": {"content": "Kirkmichael", "begin_offset": 434}, "type": 1}]}, {"name": "F.", "type": 1, "salience": 0.006674048490822315, "mentions": [{"text": {"content": "F.", "begin_offset": 865}, "type": 1}]}, {"name": "Lloyd", "type": 1, "salience": 0.006509475875645876, "mentions": [{"text": {"content": "Lloyd", "begin_offset": 872}, "type": 1}, {"text": {"content": "Lloyd", "begin_offset": 962}, "type": 1}]}, {"name": "Indian Rajah", "type": 3, "salience": 0.006432872731238604, "mentions": [{"text": {"content": "Indian Rajah", "begin_offset": 790}, "type": 1}]}, {"name": "trip", "type": 4, "salience": 0.005587389227002859, "mentions": [{"text": {"content": "trip", "begin_offset": 1282}, "type": 2}]}, {"name": "help", "type": 7, "salience": 0.005583098158240318, "mentions": [{"text": {"content": "help", "begin_offset": 1344}, "type": 2}]}, {"name": "health", "type": 7, "salience": 0.005583098158240318, "mentions": [{"text": {"content": "health", "begin_offset": 1378}, "type": 2}]}, {"name": "metal", "type": 7, "salience": 0.005583098158240318, "mentions": [{"text": {"content": "metal", "begin_offset": 1439}, "type": 2}]}, {"name": "R.L.S.P.S.", "type": 7, "salience": 0.005465259309858084, "mentions": [{"text": {"content": "R. L. S.\nP.S.", "begin_offset": 1207}, "type": 1}]}, {"name": "piano", "type": 6, "salience": 0.0040612127631902695, "mentions": [{"text": {"content": "piano", "begin_offset": 1004}, "type": 2}]}, {"name": "penny whistle", "type": 7, "salience": 0.0040612127631902695, "mentions": [{"text": {"content": "penny whistle", "begin_offset": 975}, "type": 2}]}, {"name": "piano", "type": 6, "salience": 0.004053284414112568, "mentions": [{"text": {"content": "piano", "begin_offset": 1069}, "type": 2}]}, {"name": "change", "type": 7, "salience": 0.0038657826371490955, "mentions": [{"text": {"content": "change", "begin_offset": 1422}, "type": 2}]}, {"name": "R.L.S.", "type": 7, "metadata": {"mid": "/m/01jyld", "wikipedia_url": "https://en.wikipedia.org/wiki/Restless_legs_syndrome"}, "salience": 0.0037754299119114876, "mentions": [{"text": {"content": "R. L. S.", "begin_offset": 1446}, "type": 1}]}, {"name": "concerto", "type": 7, "salience": 0.003549561370164156, "mentions": [{"text": {"content": "concerto", "begin_offset": 1031}, "type": 2}]}, {"name": "powers", "type": 7, "salience": 0.003549561370164156, "mentions": [{"text": {"content": "powers", "begin_offset": 1016}, "type": 2}]}]