{"document_sentiment": {"magnitude": 3.5999999046325684}, "language": "en", "sentences": [{"text": {"content": "Letter: TO A. ST."}, "sentiment": {}}, {"text": {"content": "GAUDENS", "begin_offset": 18}, "sentiment": {}}, {"text": {"content": "VAILIMA, SAMOA, JULY 8, 1894.", "begin_offset": 27}, "sentiment": {}}, {"text": {"content": "MY DEAR ST.", "begin_offset": 57}, "sentiment": {}}, {"text": {"content": "GAUDENS, - This is to tell you that the medallion has been at last triumphantly transported up the hill and placed over my smoking-room mantelpiece.", "begin_offset": 69}, "sentiment": {"magnitude": 0.4000000059604645, "score": -0.4000000059604645}}, {"text": {"content": "It is considered by everybody a first-rate but flattering portrait.", "begin_offset": 218}, "sentiment": {"magnitude": 0.10000000149011612, "score": 0.10000000149011612}}, {"text": {"content": "We have it in a very good light, which brings out the artistic merits of the god-like sculptor to great advantage.", "begin_offset": 286}, "sentiment": {"magnitude": 0.8999999761581421, "score": 0.8999999761581421}}, {"text": {"content": "As for my own opinion, I believe it to be a speaking likeness, and not flattered at all; possibly a little the reverse.", "begin_offset": 401}, "sentiment": {"magnitude": 0.800000011920929, "score": -0.800000011920929}}, {"text": {"content": "The verses (curse the rhyme) look remarkably well.", "begin_offset": 521}, "sentiment": {"magnitude": 0.699999988079071, "score": 0.699999988079071}}, {"text": {"content": "Please do not longer delay, but send me an account for the expense of the gilt letters.", "begin_offset": 572}, "sentiment": {"magnitude": 0.10000000149011612, "score": 0.10000000149011612}}, {"text": {"content": "I was sorry indeed that they proved beyond the means of a small farmer.", "begin_offset": 660}, "sentiment": {}}, {"text": {"content": "- Yours very sincerely,\nROBERT LOUIS STEVENSON.", "begin_offset": 732}, "sentiment": {}}]}