{"document_sentiment": {"magnitude": 9.100000381469727}, "language": "en", "sentences": [{"text": {"content": "Letter: TO MISS ADELAIDE BOODLE"}, "sentiment": {"magnitude": 0.10000000149011612, "score": 0.10000000149011612}}, {"text": {"content": "[SARANAC LAKE, APRIL 1888.]", "begin_offset": 33}, "sentiment": {}}, {"text": {"content": "ADDRESS C/O MESSRS.", "begin_offset": 61}, "sentiment": {}}, {"text": {"content": "SCRIBNER'S SONS, 743 BROADWAY, N.Y.", "begin_offset": 81}, "sentiment": {}}, {"text": {"content": "MY DEAR GAMEKEEPER, - Your p. c.", "begin_offset": 117}, "sentiment": {"magnitude": 0.10000000149011612, "score": 0.10000000149011612}}, {"text": {"content": "(proving you a good student of Micawber) has just arrived, and it paves the way to something I am anxious to say.", "begin_offset": 150}, "sentiment": {"magnitude": 0.4000000059604645, "score": 0.4000000059604645}}, {"text": {"content": "I wrote a paper the other day - PULVIS ET UMBRA; - I wrote it with great feeling and conviction: to me it seemed bracing and healthful, it is in such a world (so seen by me), that I am very glad to fight out my battle, and see some fine sunsets, and hear some excellent jests between whiles round the camp fire.", "begin_offset": 264}, "sentiment": {"magnitude": 0.8999999761581421, "score": 0.8999999761581421}}, {"text": {"content": "But I find that to some people this vision of mine is a nightmare, and extinguishes all ground of faith in God or pleasure in man.", "begin_offset": 576}, "sentiment": {"magnitude": 0.20000000298023224, "score": 0.20000000298023224}}, {"text": {"content": "Truth I think not so much of; for I do not know it.", "begin_offset": 707}, "sentiment": {"magnitude": 0.10000000149011612, "score": -0.10000000149011612}}, {"text": {"content": "And I could wish in my heart that I had not published this paper, if it troubles folk too much: all have not the same digestion, nor the same sight of things.", "begin_offset": 759}, "sentiment": {"magnitude": 0.5, "score": -0.5}}, {"text": {"content": "And it came over me with special pain that perhaps this article (which I was at the pains to send to her) might give dismalness to my GAMEKEEPER AT HOME.", "begin_offset": 918}, "sentiment": {"magnitude": 0.30000001192092896, "score": -0.30000001192092896}}, {"text": {"content": "Well, I cannot take back what I have said; but yet I may add this.", "begin_offset": 1072}, "sentiment": {"magnitude": 0.30000001192092896, "score": -0.30000001192092896}}, {"text": {"content": "If my view be everything but the nonsense that it may be - to me it seems self- evident and blinding truth - surely of all things it makes this world holier.", "begin_offset": 1139}, "sentiment": {"magnitude": 0.6000000238418579, "score": -0.6000000238418579}}, {"text": {"content": "There is nothing in it but the moral side - but the great battle and the breathing times with their refreshments.", "begin_offset": 1297}, "sentiment": {"magnitude": 0.6000000238418579, "score": 0.6000000238418579}}, {"text": {"content": "I see no more and no less.", "begin_offset": 1411}, "sentiment": {}}, {"text": {"content": "And if you look again, it is not ugly, and it is filled with promise.", "begin_offset": 1438}, "sentiment": {"magnitude": 0.30000001192092896, "score": -0.30000001192092896}}, {"text": {"content": "Pray excuse a desponding author for this apology.", "begin_offset": 1508}, "sentiment": {"magnitude": 0.8999999761581421, "score": -0.8999999761581421}}, {"text": {"content": "My wife is away off to the uttermost parts of the States, all by herself.", "begin_offset": 1558}, "sentiment": {}}, {"text": {"content": "I shall be off, I hope, in a week; but where?", "begin_offset": 1632}, "sentiment": {}}, {"text": {"content": "Ah! that I know not.", "begin_offset": 1678}, "sentiment": {"magnitude": 0.30000001192092896, "score": -0.30000001192092896}}, {"text": {"content": "I keep wonderful, and my wife a little better, and the lad flourishing.", "begin_offset": 1699}, "sentiment": {"magnitude": 0.8999999761581421, "score": 0.8999999761581421}}, {"text": {"content": "We now perform duets on two D tin whistles; it is no joke to make the bass; I think I must really send you one, which I wish you would correct . . .", "begin_offset": 1771}, "sentiment": {"magnitude": 0.699999988079071, "score": 0.699999988079071}}, {"text": {"content": "I may be said to live for these instrumental labours now, but I have always some childishness on hand.", "begin_offset": 1920}, "sentiment": {"magnitude": 0.4000000059604645, "score": 0.4000000059604645}}, {"text": {"content": "- I am, dear Gamekeeper, your indulgent but intemperate Squire,\nROBERT LOUIS STEVENSON.", "begin_offset": 2023}, "sentiment": {"magnitude": 0.30000001192092896, "score": -0.30000001192092896}}]}